<?xml version="1.0" encoding="utf-8"?>
	<annotation>
		<folder>driving_annotation_dataset</folder>
		<filename>00148.jpg</filename>
		<size>
			<width>320</width>
			<height>240</height>
			<depth>3</depth>
		</size>
		<object>
			<name>smoke</name>
			<pose>Unspecified</pose>
			<truncated>0</truncated>
			<difficult>0</difficult>
			<bndbox>
				<xmin>139</xmin>
				<ymin>177</ymin>
				<xmax>190</xmax>
				<ymax>202</ymax>
			</bndbox>
		</object>
		<object>
			<name>smoke</name>
			<pose>Unspecified</pose>
			<truncated>0</truncated>
			<difficult>0</difficult>
			<bndbox>
				<xmin>191</xmin>
				<ymin>154</ymin>
				<xmax>241</xmax>
				<ymax>186</ymax>
			</bndbox>
		</object>
		<object>
			<name>smoke</name>
			<pose>Unspecified</pose>
			<truncated>0</truncated>
			<difficult>0</difficult>
			<bndbox>
				<xmin>267</xmin>
				<ymin>129</ymin>
				<xmax>321</xmax>
				<ymax>166</ymax>
			</bndbox>
		</object>
		<object>
			<name>smoke</name>
			<pose>Unspecified</pose>
			<truncated>0</truncated>
			<difficult>0</difficult>
			<bndbox>
				<xmin>244</xmin>
				<ymin>173</ymin>
				<xmax>301</xmax>
				<ymax>212</ymax>
			</bndbox>
		</object>
	</annotation>
