<?xml version="1.0" encoding="utf-8"?>
	<annotation>
		<folder>driving_annotation_dataset</folder>
		<filename>03366.jpg</filename>
		<size>
			<width>1920</width>
			<height>1080</height>
			<depth>3</depth>
		</size>
		<object>
			<name>smoke</name>
			<pose>Unspecified</pose>
			<truncated>0</truncated>
			<difficult>0</difficult>
			<bndbox>
				<xmin>1106</xmin>
				<ymin>435</ymin>
				<xmax>1331</xmax>
				<ymax>661</ymax>
			</bndbox>
		</object>
		<object>
			<name>smoke</name>
			<pose>Unspecified</pose>
			<truncated>0</truncated>
			<difficult>0</difficult>
			<bndbox>
				<xmin>1354</xmin>
				<ymin>292</ymin>
				<xmax>1880</xmax>
				<ymax>685</ymax>
			</bndbox>
		</object>
		<object>
			<name>smoke</name>
			<pose>Unspecified</pose>
			<truncated>0</truncated>
			<difficult>0</difficult>
			<bndbox>
				<xmin>1708</xmin>
				<ymin>162</ymin>
				<xmax>1915</xmax>
				<ymax>284</ymax>
			</bndbox>
		</object>
	</annotation>
