<?xml version="1.0" encoding="utf-8"?>
	<annotation>
		<folder>driving_annotation_dataset</folder>
		<filename>04798.jpg</filename>
		<size>
			<width>450</width>
			<height>300</height>
			<depth>3</depth>
		</size>
		<object>
			<name>smoke</name>
			<pose>Unspecified</pose>
			<truncated>0</truncated>
			<difficult>0</difficult>
			<bndbox>
				<xmin>156</xmin>
				<ymin>72</ymin>
				<xmax>196</xmax>
				<ymax>136</ymax>
			</bndbox>
		</object>
		<object>
			<name>smoke</name>
			<pose>Unspecified</pose>
			<truncated>0</truncated>
			<difficult>0</difficult>
			<bndbox>
				<xmin>226</xmin>
				<ymin>5</ymin>
				<xmax>369</xmax>
				<ymax>92</ymax>
			</bndbox>
		</object>
		<object>
			<name>smoke</name>
			<pose>Unspecified</pose>
			<truncated>0</truncated>
			<difficult>0</difficult>
			<bndbox>
				<xmin>298</xmin>
				<ymin>97</ymin>
				<xmax>396</xmax>
				<ymax>193</ymax>
			</bndbox>
		</object>
	</annotation>
