<?xml version="1.0" encoding="utf-8"?>
	<annotation>
		<folder>driving_annotation_dataset</folder>
		<filename>11126.jpg</filename>
		<size>
			<width>710</width>
			<height>498</height>
			<depth>3</depth>
		</size>
		<object>
			<name>smoke</name>
			<pose>Unspecified</pose>
			<truncated>0</truncated>
			<difficult>0</difficult>
			<bndbox>
				<xmin>263</xmin>
				<ymin>148</ymin>
				<xmax>434</xmax>
				<ymax>262</ymax>
			</bndbox>
		</object>
		<object>
			<name>smoke</name>
			<pose>Unspecified</pose>
			<truncated>0</truncated>
			<difficult>0</difficult>
			<bndbox>
				<xmin>319</xmin>
				<ymin>261</ymin>
				<xmax>432</xmax>
				<ymax>285</ymax>
			</bndbox>
		</object>
		<object>
			<name>smoke</name>
			<pose>Unspecified</pose>
			<truncated>0</truncated>
			<difficult>0</difficult>
			<bndbox>
				<xmin>196</xmin>
				<ymin>2</ymin>
				<xmax>325</xmax>
				<ymax>136</ymax>
			</bndbox>
		</object>
		<object>
			<name>smoke</name>
			<pose>Unspecified</pose>
			<truncated>0</truncated>
			<difficult>0</difficult>
			<bndbox>
				<xmin>327</xmin>
				<ymin>1</ymin>
				<xmax>504</xmax>
				<ymax>150</ymax>
			</bndbox>
		</object>
		<object>
			<name>smoke</name>
			<pose>Unspecified</pose>
			<truncated>0</truncated>
			<difficult>0</difficult>
			<bndbox>
				<xmin>436</xmin>
				<ymin>149</ymin>
				<xmax>487</xmax>
				<ymax>191</ymax>
			</bndbox>
		</object>
		<object>
			<name>smoke</name>
			<pose>Unspecified</pose>
			<truncated>0</truncated>
			<difficult>0</difficult>
			<bndbox>
				<xmin>329</xmin>
				<ymin>358</ymin>
				<xmax>381</xmax>
				<ymax>419</ymax>
			</bndbox>
		</object>
	</annotation>
