<?xml version="1.0" encoding="utf-8"?>
	<annotation>
		<folder>driving_annotation_dataset</folder>
		<filename>00075.jpg</filename>
		<size>
			<width>960</width>
			<height>1280</height>
			<depth>3</depth>
		</size>
		<object>
			<name>smoke</name>
			<pose>Unspecified</pose>
			<truncated>0</truncated>
			<difficult>0</difficult>
			<bndbox>
				<xmin>424</xmin>
				<ymin>620</ymin>
				<xmax>556</xmax>
				<ymax>743</ymax>
			</bndbox>
		</object>
		<object>
			<name>smoke</name>
			<pose>Unspecified</pose>
			<truncated>0</truncated>
			<difficult>0</difficult>
			<bndbox>
				<xmin>204</xmin>
				<ymin>630</ymin>
				<xmax>333</xmax>
				<ymax>687</ymax>
			</bndbox>
		</object>
		<object>
			<name>smoke</name>
			<pose>Unspecified</pose>
			<truncated>0</truncated>
			<difficult>0</difficult>
			<bndbox>
				<xmin>593</xmin>
				<ymin>637</ymin>
				<xmax>773</xmax>
				<ymax>745</ymax>
			</bndbox>
		</object>
		<object>
			<name>smoke</name>
			<pose>Unspecified</pose>
			<truncated>0</truncated>
			<difficult>0</difficult>
			<bndbox>
				<xmin>262</xmin>
				<ymin>557</ymin>
				<xmax>364</xmax>
				<ymax>617</ymax>
			</bndbox>
		</object>
		<object>
			<name>smoke</name>
			<pose>Unspecified</pose>
			<truncated>0</truncated>
			<difficult>0</difficult>
			<bndbox>
				<xmin>304</xmin>
				<ymin>700</ymin>
				<xmax>397</xmax>
				<ymax>735</ymax>
			</bndbox>
		</object>
	</annotation>
