<?xml version="1.0" encoding="utf-8"?>
	<annotation>
		<folder>driving_annotation_dataset</folder>
		<filename>01271.jpg</filename>
		<size>
			<width>181</width>
			<height>279</height>
			<depth>3</depth>
		</size>
		<object>
			<name>smoke</name>
			<pose>Unspecified</pose>
			<truncated>0</truncated>
			<difficult>0</difficult>
			<bndbox>
				<xmin>121</xmin>
				<ymin>136</ymin>
				<xmax>170</xmax>
				<ymax>198</ymax>
			</bndbox>
		</object>
		<object>
			<name>smoke</name>
			<pose>Unspecified</pose>
			<truncated>0</truncated>
			<difficult>0</difficult>
			<bndbox>
				<xmin>2</xmin>
				<ymin>31</ymin>
				<xmax>48</xmax>
				<ymax>92</ymax>
			</bndbox>
		</object>
	</annotation>
