<?xml version="1.0" encoding="utf-8"?>
	<annotation>
		<folder>driving_annotation_dataset</folder>
		<filename>02313.jpg</filename>
		<size>
			<width>1920</width>
			<height>1080</height>
			<depth>3</depth>
		</size>
		<object>
			<name>smoke</name>
			<pose>Unspecified</pose>
			<truncated>0</truncated>
			<difficult>0</difficult>
			<bndbox>
				<xmin>38</xmin>
				<ymin>232</ymin>
				<xmax>422</xmax>
				<ymax>613</ymax>
			</bndbox>
		</object>
		<object>
			<name>smoke</name>
			<pose>Unspecified</pose>
			<truncated>0</truncated>
			<difficult>0</difficult>
			<bndbox>
				<xmin>453</xmin>
				<ymin>476</ymin>
				<xmax>623</xmax>
				<ymax>751</ymax>
			</bndbox>
		</object>
		<object>
			<name>smoke</name>
			<pose>Unspecified</pose>
			<truncated>0</truncated>
			<difficult>0</difficult>
			<bndbox>
				<xmin>470</xmin>
				<ymin>749</ymin>
				<xmax>899</xmax>
				<ymax>1078</ymax>
			</bndbox>
		</object>
		<object>
			<name>smoke</name>
			<pose>Unspecified</pose>
			<truncated>0</truncated>
			<difficult>0</difficult>
			<bndbox>
				<xmin>318</xmin>
				<ymin>957</ymin>
				<xmax>454</xmax>
				<ymax>1070</ymax>
			</bndbox>
		</object>
		<object>
			<name>smoke</name>
			<pose>Unspecified</pose>
			<truncated>0</truncated>
			<difficult>0</difficult>
			<bndbox>
				<xmin>630</xmin>
				<ymin>335</ymin>
				<xmax>1692</xmax>
				<ymax>756</ymax>
			</bndbox>
		</object>
		<object>
			<name>smoke</name>
			<pose>Unspecified</pose>
			<truncated>0</truncated>
			<difficult>0</difficult>
			<bndbox>
				<xmin>913</xmin>
				<ymin>761</ymin>
				<xmax>1582</xmax>
				<ymax>1076</ymax>
			</bndbox>
		</object>
		<object>
			<name>smoke</name>
			<pose>Unspecified</pose>
			<truncated>0</truncated>
			<difficult>0</difficult>
			<bndbox>
				<xmin>1667</xmin>
				<ymin>763</ymin>
				<xmax>1895</xmax>
				<ymax>1039</ymax>
			</bndbox>
		</object>
		<object>
			<name>smoke</name>
			<pose>Unspecified</pose>
			<truncated>0</truncated>
			<difficult>0</difficult>
			<bndbox>
				<xmin>844</xmin>
				<ymin>64</ymin>
				<xmax>1080</xmax>
				<ymax>337</ymax>
			</bndbox>
		</object>
		<object>
			<name>smoke</name>
			<pose>Unspecified</pose>
			<truncated>0</truncated>
			<difficult>0</difficult>
			<bndbox>
				<xmin>1082</xmin>
				<ymin>5</ymin>
				<xmax>1286</xmax>
				<ymax>201</ymax>
			</bndbox>
		</object>
		<object>
			<name>smoke</name>
			<pose>Unspecified</pose>
			<truncated>0</truncated>
			<difficult>0</difficult>
			<bndbox>
				<xmin>1308</xmin>
				<ymin>5</ymin>
				<xmax>1552</xmax>
				<ymax>181</ymax>
			</bndbox>
		</object>
		<object>
			<name>smoke</name>
			<pose>Unspecified</pose>
			<truncated>0</truncated>
			<difficult>0</difficult>
			<bndbox>
				<xmin>1099</xmin>
				<ymin>211</ymin>
				<xmax>1576</xmax>
				<ymax>329</ymax>
			</bndbox>
		</object>
	</annotation>
