<?xml version="1.0" encoding="utf-8"?>
	<annotation>
		<folder>driving_annotation_dataset</folder>
		<filename>20840.jpg</filename>
		<size>
			<width>1920</width>
			<height>1080</height>
			<depth>3</depth>
		</size>
		<object>
			<name>smoke</name>
			<pose>Unspecified</pose>
			<truncated>0</truncated>
			<difficult>0</difficult>
			<bndbox>
				<xmin>815</xmin>
				<ymin>780</ymin>
				<xmax>983</xmax>
				<ymax>949</ymax>
			</bndbox>
		</object>
		<object>
			<name>smoke</name>
			<pose>Unspecified</pose>
			<truncated>0</truncated>
			<difficult>0</difficult>
			<bndbox>
				<xmin>1055</xmin>
				<ymin>887</ymin>
				<xmax>1135</xmax>
				<ymax>994</ymax>
			</bndbox>
		</object>
		<object>
			<name>smoke</name>
			<pose>Unspecified</pose>
			<truncated>0</truncated>
			<difficult>0</difficult>
			<bndbox>
				<xmin>1149</xmin>
				<ymin>807</ymin>
				<xmax>1259</xmax>
				<ymax>959</ymax>
			</bndbox>
		</object>
	</annotation>
